frappyflaskcontent/__init__.py
frappyflaskcontent/content_api.py
frappyflaskcontent-1.1.1.dist-info/LICENSE
frappyflaskcontent-1.1.1.dist-info/METADATA
frappyflaskcontent-1.1.1.dist-info/WHEEL
frappyflaskcontent-1.1.1.dist-info/top_level.txt
frappyflaskcontent-1.1.1.dist-info/RECORD
