Metadata-Version: 2.1
Name: frappyflaskcontent
Version: 1.1.1
Summary: Flask Endpoints for Content Management and Retrieval
Home-page: https://github.com/ilfrich/frappy-flask-content
Author: Peter Ilfrich
Author-email: das-peter@gmx.de
License: UNKNOWN
Platform: UNKNOWN
Requires-Dist: flask
Requires-Dist: pbu (>=1.0.0)
